setup.py
umls_request_manager/__init__.py
umls_request_manager/umls_auth.py
umls_request_manager/umls_request_manager.py
umls_request_manager.egg-info/PKG-INFO
umls_request_manager.egg-info/SOURCES.txt
umls_request_manager.egg-info/dependency_links.txt
umls_request_manager.egg-info/not-zip-safe
umls_request_manager.egg-info/requires.txt
umls_request_manager.egg-info/top_level.txt